pywcat/PIL.py
pywcat/__init__.py
pywcat/bokeh.py
pywcat/matplotlib.py
pywcat/server.py
pywcat-0.3.0.dist-info/METADATA
pywcat-0.3.0.dist-info/WHEEL
pywcat-0.3.0.dist-info/top_level.txt
pywcat-0.3.0.dist-info/RECORD
