Metadata-Version: 2.1
Name: pywcat
Version: 0.3.0
Summary: Read the latest Real Python tutorials
Home-page: https://github.com/olivercoad/wcat
Author: Oliver Coad
Author-email: oliver.coad@gmail.com
License: MIT
Platform: UNKNOWN
Classifier: License :: OSI Approved :: MIT License
Classifier: Programming Language :: Python :: 3
Classifier: Programming Language :: Python :: 3.7
Requires-Dist: requests
